smriprep_docker.py
smriprep_docker-0.19.2.dist-info/licenses/LICENSE
smriprep_docker-0.19.2.dist-info/METADATA
smriprep_docker-0.19.2.dist-info/WHEEL
smriprep_docker-0.19.2.dist-info/entry_points.txt
smriprep_docker-0.19.2.dist-info/top_level.txt
smriprep_docker-0.19.2.dist-info/RECORD
