Metadata-Version: 2.4
Name: smriprep-docker
Version: 0.19.2
Summary: A wrapper for generating Docker commands using regular sMRIPrep syntax
Home-page: https://github.com/nipreps/smriprep
Author: The NiPreps developers
Author-email: nipreps@gmail.com
Maintainer: Christopher J. Markiewicz
Maintainer-email: nipreps@gmail.com
License: 3-clause BSD
Classifier: Development Status :: 4 - Beta
Classifier: Intended Audience :: Science/Research
Classifier: License :: OSI Approved :: BSD License
Classifier: Programming Language :: Python :: 2
Classifier: Programming Language :: Python :: 3
License-File: LICENSE
Dynamic: license-file
